pymfl
test
