Metadata-Version: 2.1
Name: pymfl
Version: 1.0.2
Summary: Python wrapper for the myfantasyleague API.
Author: Joey Greco
Author-email: joeyagreco@gmail.com
License: MIT
License-File: LICENSE
